kaleidoscope_sdk/__init__.py
kaleidoscope_sdk/kaleidoscope_api.py
kaleidoscope_sdk-0.1.0.dist-info/METADATA
kaleidoscope_sdk-0.1.0.dist-info/WHEEL
kaleidoscope_sdk-0.1.0.dist-info/top_level.txt
kaleidoscope_sdk-0.1.0.dist-info/RECORD
