Metadata-Version: 2.2
Name: kaleidoscope-sdk
Version: 0.1.0
Summary: A Python SDK for the Kaleidoscope API
Home-page: https://github.com/kaleidoscope-cloud/kaleidoscope-sdk.git
Author: Kaleidoscope
Author-email: support@kscope.io
Classifier: Programming Language :: Python :: 3
Classifier: License :: OSI Approved :: MIT License
Classifier: Operating System :: OS Independent
Requires-Python: >=3.6
Requires-Dist: requests>=2.25.1
Dynamic: author
Dynamic: author-email
Dynamic: classifier
Dynamic: description
Dynamic: description-content-type
Dynamic: home-page
Dynamic: requires-dist
Dynamic: requires-python
Dynamic: summary
